larry/__init__.py
larry/dynamo.py
larry/iam.py
larry/lmbda.py
larry/s3.py
larry/sagemaker.py
larry/sfn.py
larry/sqs.py
larry/sts.py
larry/textract.py
larry/types.py
larry/core/__init__.py
larry/core/ipython.py
larry/mturk/Assignment.py
larry/mturk/HIT.py
larry/mturk/__init__.py
larry/mturk/consolidate.py
larry/utils/__init__.py
larry/utils/dispatch.py
larry/utils/image.py
larry-0.2.12.dist-info/LICENSE
larry-0.2.12.dist-info/METADATA
larry-0.2.12.dist-info/WHEEL
larry-0.2.12.dist-info/top_level.txt
larry-0.2.12.dist-info/RECORD
