Metadata-Version: 2.1
Name: larry
Version: 0.2.12
Summary: Library of helper reference for common data tasks using AWS resources such as S3, MTurk and others
Home-page: https://github.com/dschultz0/larry
Author: Dave Schultz
Author-email: djschult@gmail.com
License: UNKNOWN
Keywords: larry data aws boto3 mturk s3
Platform: UNKNOWN
Classifier: Programming Language :: Python :: 3
Classifier: License :: OSI Approved :: MIT License
Classifier: Operating System :: OS Independent
License-File: LICENSE
